README.md
setup.cfg
setup.py
amesh/__init__.py
amesh/entry.py
amesh.egg-info/PKG-INFO
amesh.egg-info/SOURCES.txt
amesh.egg-info/dependency_links.txt
amesh.egg-info/requires.txt
amesh.egg-info/top_level.txt
bin/amesh