Metadata-Version: 1.1
Name: amesh
Version: 0.2.0
Summary: みんな大好き東京アメッシュ
Home-page: https://github.com/otiai10/amesh.py
Author: Hiromu OCHIAI
Author-email: otiai10@gmail.com
License: MIT
Keywords: amesh,python
Platform: UNKNOWN
Classifier: Development Status :: 4 - Beta
Classifier: Intended Audience :: Developers
Classifier: License :: OSI Approved :: MIT License
Classifier: Programming Language :: Python :: 3
Classifier: Programming Language :: Python :: 3.6
